Workbook

Sheet Data
A1: Gear Assembly | B1: GA Category | C1: Month | D1: Quarter | E1: Fiscal Year | F1: Quantity Produced | G1: Sales Quantity | H1: Price | I1: Amount Sold | J1: Unit Cost | K1: % Margin
A2: Gear Assembly 1 (BS4) | B2: BS4 Only | C2: April | D2: Q1 | E2: 2019-20 | F2: 6393 | G2: 6099 | H2: 544 | I2: =G2*H2 -> 3317856 | J2: =SUMIFS(Cost!$I:$I, Cost!$A:$A, A2, Cost!$B:$B, E2) -> 395 | K2: =(H2-J2)/H2 -> 0.27389706 | L2: {=(H2:H175 - J2:J175) / H2:H175} -> #VALUE!
A3: Gear Assembly 1 (BS4) | B3: BS4 Only | C3: May | D3: Q1 | E3: 2019-20 | F3: 5891 | G3: 5322 | H3: 513 | I3: =G3*H3 -> 2730186 | J3: =SUMIFS(Cost!$I:$I, Cost!$A:$A, A3, Cost!$B:$B, E3) -> 395 | K3: =(H3-J3)/H3 -> 0.23001949
A4: Gear Assembly 1 (BS4) | B4: BS4 Only | C4: June | D4: Q1 | E4: 2019-20 | F4: 6791 | G4: 5953 | H4: 427 | I4: =G4*H4 -> 2541931 | J4: =SUMIFS(Cost!$I:$I, Cost!$A:$A, A4, Cost!$B:$B, E4) -> 395 | K4: =(H4-J4)/H4 -> 0.074941452
A5: Gear Assembly 1 (BS4) | B5: BS4 Only | C5: July | D5: Q2 | E5: 2019-20 | F5: 5667 | G5: 4962 | H5: 378 | I5: =G5*H5 -> 1875636 | J5: =SUMIFS(Cost!$I:$I, Cost!$A:$A, A5, Cost!$B:$B, E5) -> 395 | K5: =(H5-J5)/H5 -> -0.044973545
A6: Gear Assembly 1 (BS4) | B6: BS4 Only | C6: August | D6: Q2 | E6: 2019-20 | F6: 6555 | G6: 6447 | H6: 566 | I6: =G6*H6 -> 3649002 | J6: =SUMIFS(Cost!$I:$I, Cost!$A:$A, A6, Cost!$B:$B, E6) -> 395 | K6: =(H6-J6)/H6 -> 0.30212014
A7: Gear Assembly 1 (BS4) | B7: BS4 Only | C7: September | D7: Q2 | E7: 2019-20 | F7: 5306 | G7: 4893 | H7: 354 | I7: =G7*H7 -> 1732122 | J7: =SUMIFS(Cost!$I:$I, Cost!$A:$A, A7, Cost!$B:$B, E7) -> 395 | K7: =(H7-J7)/H7 -> -0.11581921
A8: Gear Assembly 1 (BS4) | B8: BS4 Only | C8: October | D8: Q3 | E8: 2019-20 | F8: 5725 | G8: 5478 | H8: 539 | I8: =G8*H8 -> 2952642 | J8: =SUMIFS(Cost!$I:$I, Cost!$A:$A, A8, Cost!$B:$B, E8) -> 395 | K8: =(H8-J8)/H8 -> 0.26716141 | L8: =_xlfn.MAXIFS(G2:G175, B2:B175, "BS4 Only", D2:D175, "Q1") -> 6388
A9: Gear Assembly 1 (BS4) | B9: BS4 Only | C9: November | D9: Q3 | E9: 2019-20 | F9: 5870 | G9: 5311 | H9: 379 | I9: =G9*H9 -> 2012869 | J9: =SUMIFS(Cost!$I:$I, Cost!$A:$A, A9, Cost!$B:$B, E9) -> 395 | K9: =(H9-J9)/H9 -> -0.042216359
A10: Gear Assembly 1 (BS4) | B10: BS4 Only | C10: December | D10: Q3 | E10: 2019-20 | F10: 5937 | G10: 5287 | H10: 474 | I10: =G10*H10 -> 2506038 | J10: =SUMIFS(Cost!$I:$I, Cost!$A:$A, A10, Cost!$B:$B, E10) -> 395 | K10: =(H10-J10)/H10 -> 0.16666667
A11: Gear Assembly 1 (BS4) | B11: BS4 Only | C11: January | D11: Q4 | E11: 2019-20 | F11: 6629 | G11: 6211 | H11: 471 | I11: =G11*H11 -> 2925381 | J11: =SUMIFS(Cost!$I:$I, Cost!$A:$A, A11, Cost!$B:$B, E11) -> 395 | K11: =(H11-J11)/H11 -> 0.16135881
A12: Gear Assembly 1 (BS4) | B12: BS4 Only | C12: February | D12: Q4 | E12: 2019-20 | F12: 6629 | G12: 5908 | H12: 433 | I12: =G12*H12 -> 2558164 | J12: =SUMIFS(Cost!$I:$I, Cost!$A:$A, A12, Cost!$B:$B, E12) -> 395 | K12: =(H12-J12)/H12 -> 0.087759815
A13: Gear Assembly 1 (BS4) | B13: BS4 Only | C13: March | D13: Q4 | E13: 2019-20 | F13: 6573 | G13: 6225 | H13: 412 | I13: =G13*H13 -> 2564700 | J13: =SUMIFS(Cost!$I:$I, Cost!$A:$A, A13, Cost!$B:$B, E13) -> 395 | K13: =(H13-J13)/H13 -> 0.041262136
A14: Gear Assembly 1 (BS4) | B14: BS4 Only | C14: April | D14: Q1 | E14: 2020-21 | F14: 5372 | G14: 4999 | H14: 499 | I14: =G14*H14 -> 2494501 | J14: =SUMIFS(Cost!$I:$I, Cost!$A:$A, A14, Cost!$B:$B, E14) -> 444 | K14: =(H14-J14)/H14 -> 0.11022044
A15: Gear Assembly 1 (BS4) | B15: BS4 Only | C15: May | D15: Q1 | E15: 2020-21 | F15: 6193 | G15: 5212 | H15: 461 | I15: =G15*H15 -> 2402732 | J15: =SUMIFS(Cost!$I:$I, Cost!$A:$A, A15, Cost!$B:$B, E15) -> 444 | K15: =(H15-J15)/H15 -> 0.036876356
A16: Gear Assembly 1 (BS4) | B16: BS4 Only | C16: June | D16: Q1 | E16: 2020-21 | F16: 5392 | G16: 4995 | H16: 360 | I16: =G16*H16 -> 1798200 | J16: =SUMIFS(Cost!$I:$I, Cost!$A:$A, A16, Cost!$B:$B, E16) -> 444 | K16: =(H16-J16)/H16 -> -0.23333333
A17: Gear Assembly 1 (BS4) | B17: BS4 Only | C17: July | D17: Q2 | E17: 2020-21 | F17: 6153 | G17: 5599 | H17: 493 | I17: =G17*H17 -> 2760307 | J17: =SUMIFS(Cost!$I:$I, Cost!$A:$A, A17, Cost!$B:$B, E17) -> 444 | K17: =(H17-J17)/H17 -> 0.099391481
A18: Gear Assembly 1 (BS4) | B18: BS4 Only | C18: August | D18: Q2 | E18: 2020-21 | F18: 6684 | G18: 5741 | H18: 493 | I18: =G18*H18 -> 2830313 | J18: =SUMIFS(Cost!$I:$I, Cost!$A:$A, A18, Cost!$B:$B, E18) -> 444 | K18: =(H18-J18)/H18 -> 0.099391481
A19: Gear Assembly 1 (BS4) | B19: BS4 Only | C19: September | D19: Q2 | E19: 2020-21 | F19: 6227 | G19: 5959 | H19: 497 | I19: =G19*H19 -> 2961623 | J19: =SUMIFS(Cost!$I:$I, Cost!$A:$A, A19, Cost!$B:$B, E19) -> 444 | K19: =(H19-J19)/H19 -> 0.10663984
A20: Gear Assembly 1 (BS4) | B20: BS4 Only | C20: October | D20: Q3 | E20: 2020-21 | F20: 6368 | G20: 6197 | H20: 565 | I20: =G20*H20 -> 3501305 | J20: =SUMIFS(Cost!$I:$I, Cost!$A:$A, A20, Cost!$B:$B, E20) -> 444 | K20: =(H20-J20)/H20 -> 0.21415929
... A175: Gear Assembly 6 (BS6) | B175: BS6 Only | C175: August | D175: Q2 | E175: 2021-22 | F175: 6145 | G175: 5699 | H175: 534 | I175: =G175*H175 -> 3043266 | J175: =SUMIFS(Cost!$I:$I, Cost!$A:$A, A175, Cost!$B:$B, E175) -> 505 | K175: =(H175-J175)/H175 -> 0.054307116

Sheet Cost
A1: SALES DETAILS (GEAR ASSEMBLIES) | B1: FY | C1: CC | D1: Direct Materials | E1: Direct Labour | F1: Production Overhead | G1: G&A Overhead | H1: Finance Costs | I1: Total Cost | J1: Min Selling Price | K1: Net Loss | L1: Max % Margin
A2: Gear Assembly 1 (BS4) | B2: 2019-20 | C2: =CONCATENATE(A2,B2) -> Gear Assembly 1 (BS4)2019-20 | D2: 155 | E2: 48 | F2: 114 | G2: 46 | H2: 32 | I2: =SUM(D2:H2) -> 395 | J2: =_xlfn.MINIFS(Data!$H$2:$H$175, Data!$A$2:$A$175, "Gear Assembly 1 (BS4)", Data!$E$2:$E$175, "2019-20") -> 354 | K2: =J2-I2 -> -41 | L2: {=MAX((Data!H2:H175 - J2:J175) / Data!H2:H175)} -> #VALUE!
A3: Gear Assembly 2 (BS4) | B3: 2019-20 | C3: =CONCATENATE(A3,B3) -> Gear Assembly 2 (BS4)2019-20 | D3: 143 | E3: 52 | F3: 81 | G3: 46 | H3: 27 | I3: =SUM(D3:H3) -> 349 | J3: =_xlfn.MINIFS(Data!$H$2:$H$175, Data!$A$2:$A$175, "Gear Assembly 2 (BS4)", Data!$E$2:$E$175, "2019-20") -> 334 | K3: =J3-I3 -> -15 | L3: =SUMIFS(Cost!$I:$I, Cost!$A:$A, A3, Cost!$B:$B, E3) -> 0
A4: Gear Assembly 3 (BS4/6) | B4: 2019-20 | C4: =CONCATENATE(A4,B4) -> Gear Assembly 3 (BS4/6)2019-20 | D4: 200 | E4: 69 | F4: 119 | G4: 45 | H4: 32 | I4: =SUM(D4:H4) -> 465 | J4: =_xlfn.MINIFS(Data!$H$2:$H$175, Data!$A$2:$A$175, "Gear Assembly 3 (BS4/6)", Data!$E$2:$E$175, "2019-20") -> 364 | K4: =J4-I4 -> -101 | L4: =SUMIFS(Cost!$I:$I, Cost!$A:$A, A4, Cost!$B:$B, E4) -> 0
A5: Gear Assembly 4 (BS4/6) | B5: 2019-20 | C5: =CONCATENATE(A5,B5) -> Gear Assembly 4 (BS4/6)2019-20 | D5: 145 | E5: 46 | F5: 110 | G5: 45 | H5: 30 | I5: =SUM(D5:H5) -> 376 | J5: =_xlfn.MINIFS(Data!$H$2:$H$175, Data!$A$2:$A$175, "Gear Assembly 4 (BS4/6)", Data!$E$2:$E$175, "2019-20") -> 328 | K5: =J5-I5 -> -48 | L5: =SUMIFS(Cost!$I:$I, Cost!$A:$A, A5, Cost!$B:$B, E5) -> 0
A6: Gear Assembly 5 (BS6) | B6: 2019-20 | C6: =CONCATENATE(A6,B6) -> Gear Assembly 5 (BS6)2019-20 | D6: 132 | E6: 50 | F6: 70 | G6: 48 | H6: 26 | I6: =SUM(D6:H6) -> 326 | J6: =_xlfn.MINIFS(Data!$H$2:$H$175, Data!$A$2:$A$175, "Gear Assembly 5 (BS6)", Data!$E$2:$E$175, "2019-20") -> 360 | K6: =J6-I6 -> 34 | L6: =SUMIFS(Cost!$I:$I, Cost!$A:$A, A6, Cost!$B:$B, E6) -> 0
A7: Gear Assembly 6 (BS6) | B7: 2019-20 | C7: =CONCATENATE(A7,B7) -> Gear Assembly 6 (BS6)2019-20 | D7: 174 | E7: 68 | F7: 110 | G7: 46 | H7: 31 | I7: =SUM(D7:H7) -> 429 | J7: =_xlfn.MINIFS(Data!$H$2:$H$175, Data!$A$2:$A$175, "Gear Assembly 6 (BS6)", Data!$E$2:$E$175, "2019-20") -> 360 | K7: =J7-I7 -> -69 | L7: =SUMIFS(Cost!$I:$I, Cost!$A:$A, A7, Cost!$B:$B, E7) -> 0
A8: Gear Assembly 1 (BS4) | B8: 2020-21 | C8: =CONCATENATE(A8,B8) -> Gear Assembly 1 (BS4)2020-21 | D8: 199 | E8: 53 | F8: 111 | G8: 49 | H8: 32 | I8: =SUM(D8:H8) -> 444 | J8: =_xlfn.MINIFS(Data!$H$2:$H$175, Data!$A$2:$A$175, "Gear Assembly 1 (BS4)", Data!$E$2:$E$175, "2020-21") -> 360 | K8: =J8-I8 -> -84 | L8: =SUMIFS(Cost!$I:$I, Cost!$A:$A, A8, Cost!$B:$B, E8) -> 0
A9: Gear Assembly 2 (BS4) | B9: 2020-21 | C9: =CONCATENATE(A9,B9) -> Gear Assembly 2 (BS4)2020-21 | D9: 166 | E9: 57 | F9: 78 | G9: 48 | H9: 25 | I9: =SUM(D9:H9) -> 374 | J9: =_xlfn.MINIFS(Data!$H$2:$H$175, Data!$A$2:$A$175, "Gear Assembly 2 (BS4)", Data!$E$2:$E$175, "2020-21") -> 331 | K9: =J9-I9 -> -43 | L9: =SUMIFS(Cost!$I:$I, Cost!$A:$A, A9, Cost!$B:$B, E9) -> 0
A10: Gear Assembly 3 (BS4/6) | B10: 2020-21 | C10: =CONCATENATE(A10,B10) -> Gear Assembly 3 (BS4/6)2020-21 | D10: 231 | E10: 79 | F10: 124 | G10: 49 | H10: 32 | I10: =SUM(D10:H10) -> 515 | J10: =_xlfn.MINIFS(Data!$H$2:$H$175, Data!$A$2:$A$175, "Gear Assembly 3 (BS4/6)", Data!$E$2:$E$175, "2020-21") -> 360 | K10: =J10-I10 -> -155 | L10: =SUMIFS(Cost!$I:$I, Cost!$A:$A, A10, Cost!$B:$B, E10) -> 0
A11: Gear Assembly 4 (BS4/6) | B11: 2020-21 | C11: =CONCATENATE(A11,B11) -> Gear Assembly 4 (BS4/6)2020-21 | D11: 174 | E11: 56 | F11: 112 | G11: 47 | H11: 31 | I11: =SUM(D11:H11) -> 420 | J11: =_xlfn.MINIFS(Data!$H$2:$H$175, Data!$A$2:$A$175, "Gear Assembly 4 (BS4/6)", Data!$E$2:$E$175, "2020-21") -> 374 | K11: =J11-I11 -> -46 | L11: =SUMIFS(Cost!$I:$I, Cost!$A:$A, A11, Cost!$B:$B, E11) -> 0
A12: Gear Assembly 5 (BS6) | B12: 2020-21 | C12: =CONCATENATE(A12,B12) -> Gear Assembly 5 (BS6)2020-21 | D12: 176 | E12: 56 | F12: 69 | G12: 49 | H12: 25 | I12: =SUM(D12:H12) -> 375 | J12: =_xlfn.MINIFS(Data!$H$2:$H$175, Data!$A$2:$A$175, "Gear Assembly 5 (BS6)", Data!$E$2:$E$175, "2020-21") -> 344 | K12: =J12-I12 -> -31 | L12: =SUMIFS(Cost!$I:$I, Cost!$A:$A, A12, Cost!$B:$B, E12) -> 0
A13: Gear Assembly 6 (BS6) | B13: 2020-21 | C13: =CONCATENATE(A13,B13) -> Gear Assembly 6 (BS6)2020-21 | D13: 222 | E13: 76 | F13: 114 | G13: 49 | H13: 31 | I13: =SUM(D13:H13) -> 492 | J13: =_xlfn.MINIFS(Data!$H$2:$H$175, Data!$A$2:$A$175, "Gear Assembly 6 (BS6)", Data!$E$2:$E$175, "2020-21") -> 344 | K13: =J13-I13 -> -148 | L13: =SUMIFS(Cost!$I:$I, Cost!$A:$A, A13, Cost!$B:$B, E13) -> 0
A14: Gear Assembly 1 (BS4) | B14: 2021-22 | C14: =CONCATENATE(A14,B14) -> Gear Assembly 1 (BS4)2021-22 | D14: 203 | E14: 54 | F14: 127 | G14: 52 | H14: 33 | I14: =SUM(D14:H14) -> 469 | J14: =_xlfn.MINIFS(Data!$H$2:$H$175, Data!$A$2:$A$175, "Gear Assembly 1 (BS4)", Data!$E$2:$E$175, "2021-22") -> 381 | K14: =J14-I14 -> -88 | L14: =SUMIFS(Cost!$I:$I, Cost!$A:$A, A14, Cost!$B:$B, E14) -> 0
A15: Gear Assembly 2 (BS4) | B15: 2021-22 | C15: =CONCATENATE(A15,B15) -> Gear Assembly 2 (BS4)2021-22 | D15: 168 | E15: 59 | F15: 99 | G15: 52 | H15: 28 | I15: =SUM(D15:H15) -> 406 | J15: =_xlfn.MINIFS(Data!$H$2:$H$175, Data!$A$2:$A$175, "Gear Assembly 2 (BS4)", Data!$E$2:$E$175, "2021-22") -> 420 | K15: =J15-I15 -> 14 | L15: =SUMIFS(Cost!$I:$I, Cost!$A:$A, A15, Cost!$B:$B, E15) -> 0
A16: Gear Assembly 3 (BS4/6) | B16: 2021-22 | C16: =CONCATENATE(A16,B16) -> Gear Assembly 3 (BS4/6)2021-22 | D16: 249 | E16: 79 | F16: 149 | G16: 54 | H16: 36 | I16: =SUM(D16:H16) -> 567 | J16: =_xlfn.MINIFS(Data!$H$2:$H$175, Data!$A$2:$A$175, "Gear Assembly 3 (BS4/6)", Data!$E$2:$E$175, "2021-22") -> 334 | K16: =J16-I16 -> -233 | L16: =SUMIFS(Cost!$I:$I, Cost!$A:$A, A16, Cost!$B:$B, E16) -> 0
A17: Gear Assembly 4 (BS4/6) | B17: 2021-22 | C17: =CONCATENATE(A17,B17) -> Gear Assembly 4 (BS4/6)2021-22 | D17: 174 | E17: 53 | F17: 136 | G17: 51 | H17: 34 | I17: =SUM(D17:H17) -> 448 | J17: =_xlfn.MINIFS(Data!$H$2:$H$175, Data!$A$2:$A$175, "Gear Assembly 4 (BS4/6)", Data!$E$2:$E$175, "2021-22") -> 404 | K17: =J17-I17 -> -44 | L17: =SUMIFS(Cost!$I:$I, Cost!$A:$A, A17, Cost!$B:$B, E17) -> 0
A18: Gear Assembly 5 (BS6) | B18: 2021-22 | C18: =CONCATENATE(A18,B18) -> Gear Assembly 5 (BS6)2021-22 | D18: 168 | E18: 59 | F18: 81 | G18: 52 | H18: 27 | I18: =SUM(D18:H18) -> 387 | J18: =_xlfn.MINIFS(Data!$H$2:$H$175, Data!$A$2:$A$175, "Gear Assembly 5 (BS6)", Data!$E$2:$E$175, "2021-22") -> 347 | K18: =J18-I18 -> -40 | L18: =SUMIFS(Cost!$I:$I, Cost!$A:$A, A18, Cost!$B:$B, E18) -> 0
A19: Gear Assembly 6 (BS6) | B19: 2021-22 | C19: =CONCATENATE(A19,B19) -> Gear Assembly 6 (BS6)2021-22 | D19: 206 | E19: 80 | F19: 131 | G19: 53 | H19: 35 | I19: =SUM(D19:H19) -> 505 | J19: =_xlfn.MINIFS(Data!$H$2:$H$175, Data!$A$2:$A$175, "Gear Assembly 6 (BS6)", Data!$E$2:$E$175, "2021-22") -> 378 | K19: =J19-I19 -> -127 | L19: =SUMIFS(Cost!$I:$I, Cost!$A:$A, A19, Cost!$B:$B, E19) -> 0
J20: maximum loss | K20: {=MAX(ABS(K2:K19))} -> 233

Sheet Shift_Running
A1: Date | B1: Shift 1 (8 Hours) | C1: Shift 2 (8 Hours) | D1: Shift 3 (8 Hours)
A2: 44652 | B2: Unplanned Maintenance | C2: Operational | D2: Operational
A3: 44653 | B3: Power Cut | C3: Power Cut | D3: Power Cut
A4: 44654 | B4: Operational | C4: Operational | D4: Operational
A5: 44655 | B5: Operational | C5: Operational | D5: Operational
A6: 44656 | B6: Operational | C6: Operational | D6: Operational
A7: 44657 | B7: Operational | C7: Breakdown | D7: Operational
A8: 44658 | B8: Operational | C8: Operational | D8: Operational
A9: 44659 | B9: Operational | C9: Operational | D9: Operational
A10: 44660 | B10: Operational | C10: Operational | D10: Operational
A11: 44661 | B11: Operational | C11: Operational | D11: Planned Maintenance
A12: 44662 | B12: Operational | C12: Operational | D12: Operational
A13: 44663 | B13: Operational | C13: Operational | D13: Operational
... A15: 44665 | B15: Operational | C15: Operational | D15: Operational

Sheet Actual_Output
A1: Date | B1: Shift 1 | C1: Shift 2 | D1: Shift 3
A2: 44652 | B2: 0 | C2: 4035 | D2: 4320
A3: 44653 | B3: 0 | C3: 0 | D3: 0
A4: 44654 | B4: 4005 | C4: 4120 | D4: 4189
A5: 44655 | B5: 4180 | C5: 4208 | D5: 4361
A6: 44656 | B6: 4009 | C6: 4260 | D6: 4536
A7: 44657 | B7: 4400 | C7: 0 | D7: 4360
A8: 44658 | B8: 4227 | C8: 3955 | D8: 4422
A9: 44659 | B9: 4110 | C9: 4314 | D9: 4618
A10: 44660 | B10: 4375 | C10: 4162 | D10: 4285
A11: 44661 | B11: 3955 | C11: 4117 | D11: 0
A12: 44662 | B12: 4001 | C12: 4026 | D12: 4661
A13: 44663 | B13: 4240 | C13: 4233 | D13: 4089
... A15: 44665 | B15: 4325 | C15: 4285 | D15: 4249

Sheet Scrap
A1: Date | B1: Shift 1 | C1: Shift 2 | D1: Shift 3
A2: 44652 | B2: 0 | C2: 26 | D2: 21
A3: 44653 | B3: 0 | C3: 0 | D3: 0
A4: 44654 | B4: 6 | C4: 21 | D4: 1
A5: 44655 | B5: 24 | C5: 33 | D5: 7
A6: 44656 | B6: 25 | C6: 26 | D6: 14
A7: 44657 | B7: 21 | C7: 0 | D7: 20
A8: 44658 | B8: 19 | C8: 26 | D8: 32
A9: 44659 | B9: 5 | C9: 22 | D9: 48
A10: 44660 | B10: 9 | C10: 4 | D10: 37
A11: 44661 | B11: 4 | C11: 34 | D11: 0
A12: 44662 | B12: 16 | C12: 21 | D12: 27
A13: 44663 | B13: 21 | C13: 33 | D13: 49
... A15: 44665 | B15: 10 | C15: 26 | D15: 17
